vcs_scanner/__init__.py
vcs_scanner/common.py
vcs_scanner/constants.py
vcs_scanner/input_parser.py
vcs_scanner/model.py
vcs_scanner/resc_worker.py
vcs_scanner/helpers/__init__.py
vcs_scanner/helpers/cli.py
vcs_scanner/helpers/env_default.py
vcs_scanner/helpers/environment_wrapper.py
vcs_scanner/helpers/finding_action.py
vcs_scanner/helpers/finding_filter.py
vcs_scanner/helpers/gitleaks_types.py
vcs_scanner/helpers/providers/__init__.py
vcs_scanner/helpers/providers/ignore_list.py
vcs_scanner/helpers/providers/rule_comment.py
vcs_scanner/helpers/providers/rule_file.py
vcs_scanner/helpers/providers/rule_tag.py
vcs_scanner/output_modules/__init__.py
vcs_scanner/output_modules/output_module.py
vcs_scanner/output_modules/rws_api_writer.py
vcs_scanner/output_modules/stdout_writer.py
vcs_scanner/secret_scanners/__init__.py
vcs_scanner/secret_scanners/celery_worker.py
vcs_scanner/secret_scanners/cli.py
vcs_scanner/secret_scanners/configuration.py
vcs_scanner/secret_scanners/git_operation.py
vcs_scanner/secret_scanners/gitleaks_wrapper.py
vcs_scanner/secret_scanners/secret_scanner.py
vcs_scanner/static/logging.ini
resc_vcs_scanner-3.7.0.dist-info/LICENSE.md
resc_vcs_scanner-3.7.0.dist-info/METADATA
resc_vcs_scanner-3.7.0.dist-info/WHEEL
resc_vcs_scanner-3.7.0.dist-info/entry_points.txt
resc_vcs_scanner-3.7.0.dist-info/top_level.txt
resc_vcs_scanner-3.7.0.dist-info/RECORD
