Metadata-Version: 2.2
Name: resc_vcs_scanner
Version: 3.7.0
Summary: Repository Scanner - Version Control System - Scanner
Home-page: https://github.com/ABNAMRO/repository-scanner
Download-URL: 
Author: ABN AMRO
Author-email: resc@nl.abnamro.com
Requires-Python: >=3.12
License-File: LICENSE.md
Requires-Dist: amqp==5.3.1
Requires-Dist: celery==5.4.0
Requires-Dist: GitPython==3.1.44
Requires-Dist: prettytable==3.14.0
Requires-Dist: pydantic==2.10.6
Requires-Dist: requests==2.32.3
Requires-Dist: tenacity==9.0.0
Requires-Dist: termcolor==2.5.0
Requires-Dist: tomlkit==0.13.2
Dynamic: requires-dist
